tileflow/__init__.py
tileflow/backends.py
tileflow/callback.py
tileflow/core.py
tileflow/examples.py
tileflow/model.py
tileflow/reconstruction.py
tileflow/tiling.py
tileflow/utils.py
tileflow-0.6.0.dist-info/METADATA
tileflow-0.6.0.dist-info/WHEEL
tileflow-0.6.0.dist-info/licenses/LICENSE
tileflow-0.6.0.dist-info/RECORD
