Metadata-Version: 2.4
Name: tileflow
Version: 0.6.0
Summary: Fast, memory-efficient image tiling and reconstruction for deep learning and scientific computing
Project-URL: Homepage, https://github.com/mantalys/tileflow
Project-URL: Repository, https://github.com/mantalys/tileflow.git
Author: TileFlow Contributors
Maintainer: TileFlow Contributors
License: MIT License
License-File: LICENSE
Keywords: computer-vision,deep-learning,image-processing,memory-efficient,scientific-computing,tiling
Classifier: Development Status :: 4 - Beta
Classifier: Intended Audience :: Developers
Classifier: Intended Audience :: Science/Research
Classifier: License :: OSI Approved :: MIT License
Classifier: Operating System :: OS Independent
Classifier: Programming Language :: Python :: 3
Classifier: Programming Language :: Python :: 3 :: Only
Classifier: Programming Language :: Python :: 3.13
Classifier: Topic :: Scientific/Engineering
Classifier: Topic :: Scientific/Engineering :: Artificial Intelligence
Classifier: Topic :: Scientific/Engineering :: Image Processing
Classifier: Topic :: Software Development :: Libraries :: Python Modules
Classifier: Typing :: Typed
Requires-Python: >=3.13
Requires-Dist: numpy>=2.2.0
Requires-Dist: zarr>=3.1.1
Provides-Extra: all
Requires-Dist: codecarbon>=2.4.0; extra == 'all'
Requires-Dist: matplotlib>=3.8.0; extra == 'all'
Requires-Dist: pandas>=2.2.0; extra == 'all'
Requires-Dist: psutil>=5.9.0; extra == 'all'
Requires-Dist: scikit-image>=0.22.0; extra == 'all'
Requires-Dist: seaborn>=0.13.0; extra == 'all'
Provides-Extra: benchmarks
Requires-Dist: matplotlib>=3.8.0; extra == 'benchmarks'
Requires-Dist: pandas>=2.2.0; extra == 'benchmarks'
Requires-Dist: scikit-image>=0.22.0; extra == 'benchmarks'
Requires-Dist: seaborn>=0.13.0; extra == 'benchmarks'
Provides-Extra: monitoring
Requires-Dist: codecarbon>=2.4.0; extra == 'monitoring'
Requires-Dist: psutil>=5.9.0; extra == 'monitoring'
